{"data":
  {"events":[
    {"id":"1",
      "name":"9 апреля во Львове впервые состоится сольный концерт Nothing But Thieves",
      "type":"public",
      "coverPicture":"https://liroom.com.ua/wp-content/uploads/2017/11/23377201_1500712529977463_1144959099_o-353x500.jpg?x23385",
      "profilePicture":"https://liroom.com.ua/wp-content/uploads/2017/11/23377201_1500712529977463_1144959099_o-353x500.jpg?x23385",
      "description":"Британская группа Nothing But Thieves выпустила свой первый альбом в 2015 году, но уже успела побывать на разогреве у Muse, Arcade Fire и выступить в Украине на U-Park Festival и Atlas Weekend. Также музыканты были уличены в съемках своих видео в Киеве. В клипах Sorry и Amsterdam ясно читаются родные горизонты.\n\n В отношении названия Broken Machine альбом очень продуманный и цельный. Тема «сломанной машины» переносится в религию, политику, социальную и личную жизнь. Например, I Was Just a Kid и I’m Not Made by Design задаются вопросом существования Бога, намекая на то, что религия – одна большая выдумка.\n\n  Сильная, многогранная и концептуальная пластинка. В этом и заслуга продюсера Майка Кросси (Twenty One Pilots и Arctic Monkeys), который знает свое дело и подтверждает свой статус, и заслуга самой группы, которая серьезно подошла к работе и избежала известного «синдрома второго альбома». В этот раз не сработало. Уже за первые недели продаж Broken Machine взлетел на второе место в британском альбомном чарте. Очевидно, что такой релиз нельзя пропустить.",
      "distance":"1934",
      "startTime":"2018-04-09T18:00:00+0200",
      "endTime":"2018-0401:00:00+0200",
      "timeFromNow":82212,
      "isCancelled":false,
      "isDraft":false,
      "category":"night life",
      "place":{"id":"165164907333772",
        "name":"Ночной клуб Malevich",
        "location":{
          "city":"Lviv",
          "country":"Ukraine",
          "latitude":49.82239443,
          "longitude":24.03263881,
          "street":"Chornovola str. 2",
          "zip":"UA-79011"
          }
      },
      "stats":{
        "attending":1000,
        "declined":0,
        "maybe":102,
        "noreply":170
      },
      "venue":{
        "id":"165164907333772",
        "name":"Ночной клуб Malevich",
        "about":null,
        "emails":["malevich@gmail.com","malevich@gmail.com"],
  "coverPicture":"https://scontent-frx5-1.xx.fbcdn.net/v/t31.0-8/23331172_1595328273868826_3373250684702512989_o.jpg?oh=ce2c3ab53bb227593789443398228e53&oe=5A97BCDF",
  "profilePicture":"https://gastroli.s3.amazonaws.com/uploads/event/new_promo_image/10915/2.jpg",
  "category":"Night Club",
  "categoryList":["Profit Organization"],
  "location":{
    "city":"Lviv",
    "country":"Ukraine",
    "latitude":49.82239443,
    "longitude":24.03263881,
    "street":"Chornovola str. 2",
    "zip":"UA-79011"
    }
    }
    },
    {"id":"2",
      "name":"Резиденция Святого Николая",
      "type":"public",
      "coverPicture":"https://moemisto.ua/uploads/media/photo_miniature/0002/47/thumb_146668_photo_miniature_huge.jpeg?1512737146",
      "profilePicture":"https://moemisto.ua/uploads/media/photo_miniature/0002/47/thumb_146668_photo_miniature_huge.jpeg?1512737146",
      "description":"В сказочной резиденции каждый сможет лично встретиться с Чудотворцем, получить сладкий подарок и сделать незабываемое фото на память.\n\n 'Море позитивного настроения и праздничные эмоции мы зафиксируем мгновенным подарочным фото. Натуральные костюмы, очаровательные декорации и настоящий дух праздника заставят поверить в сказку даже взрослых. Самое время готовить письмо к Николаю', - добавляют организаторы.\n\n К слову, родители могут передать собственный подарок, который Чудотворец вручит лично ребенку.",
      "distance":"1934",
      "startTime":"2017-12-26T12:00:00+0200",
      "endTime":"2017-12-26T23:00:00+0200",
      "timeFromNow":82212,
      "isCancelled":false,
      "isDraft":false,
      "category":"family",
      "place":{"id":"165164907333772",
        "name":"Площадь перед Оперным театром",
        "location":{
          "city":"Lviv",
          "country":"Ukraine",
          "latitude":49.82239443,
          "longitude":24.03263881,
          "street":"Svobody avenue 28",
          "zip":"UA-79011"
          }
      },
      "stats":{
        "attending":1000,
        "declined":0,
        "maybe":102,
        "noreply":170
      },
      "venue":{
        "id":"165164907333772",
        "name":"Площадь перед Оперным театром",
        "about":null,
        "emails":["square.com","square@gmail.com"],
  "coverPicture":"https://gastroli.s3.amazonaws.com/uploads/event/new_promo_image/10915/2.jpg",
  "profilePicture":"https://www.google.com.ua/url?sa=i&rct=j&q=&esrc=s&source=images&cd=&cad=rja&uact=8&ved=0ahUKEwjV59aA2_LXAhXNZ1AKHYfBDKoQjRwIBw&url=http%3A%2F%2Fzerkalo.mk.ua%2Fnovini%2Fkak-nikolaev-gotovitsya-vstretit-zimnie-prazdniki-10-dekabrya-v-gorode-otkroetsya-ledovyj-katok-i-chast-attrakcionov.html&psig=AOvVaw1eN7lRmw3jxe8sMch0C0yD&ust=1512557775904520",
  "category":"Nonprofit Organization",
  "categoryList":["Nonprofit Organization"],
  "location":{
    "city":"Lviv",
    "country":"Ukraine",
    "latitude":49.82239443,
    "longitude":24.03263881,
    "street":"Svobody avenue 28",
    "zip":"UA-79011"
    }
    }
    },
    {"id":"3",
      "name":"Сказочный зимний городок во Львове",
      "type":"public",
      "coverPicture":"https://www.rbc.ua/static/img/f/m/fmniil_650x410.jpg",
      "profilePicture":"https://www.rbc.ua/static/img/f/m/fmniil_650x410.jpg",
      "description":"Дворец Потоцких превратят в сказочный зимний городок. Он будет проходить в центре Львова с 28 декабря по 8 января. Начало - в 12.00.\n\n Посетителей ожидают заснеженные лабиринты, яркие зимние аттракционы, рождественские вкусности, сказочные представления и игры с аниматорами.\n\n 'Часть города превратят в живую сказку с декорациями, где каждый маленький гость сможет стать героем.', - добавляют организаторы. \n\n В сказочном городке будут развлечения и для взрослых. Там ежедневно с 19.00. будут проходить выступления кавер-групп, а также угощения горячими ароматными напитками.",
      "distance":"1934",
      "startTime":"2017-12-28T12:00:00+0200",
      "endTime":"2018-01-19T00:00:00+0200",
      "timeFromNow":82212,
      "isCancelled":false,
      "isDraft":false,
      "category":"family",
      "place":{"id":"165164907333772",
        "name":"Дворец Потоцких",
        "location":{
          "city":"Lviv",
          "country":"Ukraine",
          "latitude":49.82239443,
          "longitude":24.03263881,
          "street":"Kopernika str. 15",
          "zip":"UA-79011"
          }
      },
      "stats":{
        "attending":1000,
        "declined":0,
        "maybe":102,
        "noreply":170
      },
      "venue":{
        "id":"165164907333772",
        "name":"Дворец Потоцких",
        "about":null,
        "emails":["palace@gmail.com","palace@gmail.com"],
  "coverPicture":"https://moemisto.ua/uploads/media/event/0002/44/thumb_143731_event_content_photo.jpeg?1511424056",
  "profilePicture":"https://www.google.com.ua/url?sa=i&rct=j&q=&esrc=s&source=images&cd=&cad=rja&uact=8&ved=&url=https%3A%2F%2Fwww.pinterest.com%2Fsweetonsweets%2Fcarousels%2F&psig=AOvVaw1aYoUkVgjEcTT-7VSI6vsa&ust=1512557130024471",
  "category":"Nonprofit Organization",
  "categoryList":["Nonprofit Organization"],
  "location":{
    "city":"Lviv",
    "country":"Ukraine",
    "latitude":49.82239443,
    "longitude":24.03263881,
    "street":"Kopernika str. 15",
    "zip":"UA-79011"
    }
    }
    },
    {"id":"4",
      "name":"Выставка 'Вне цвета'",
      "type":"public",
      "coverPicture":"https://i2.wp.com/photo-lviv.in.ua/wp-content/uploads/2017/11/Zolota-seredina.jpg?resize=696%2C680",
      "profilePicture":"https://i0.wp.com/photo-lviv.in.ua/wp-content/uploads/2017/11/Misto-spit.jpg?resize=696%2C481",
      "description":"'Вне цвета' - так называется выставка, которую представляет во Львовском музее истории религии мастер монументальной живописи и витража Игорь Бадяк.\n\n Игорь Бадяк изучал художественную роспись во Львовском государственном колледже декоративного и прикладного искусства имени И. Труша. Окончил Львовскую национальную академию искусств (кафедра монументальной живописи). С тех пор (1992 года) непрерывно работает в области станковой, монументальной живописи (витраж, мозаика). Игорь Бадяк - участник всеукраинских и международных пленеров. Его работы есть в музейных и частных коллекциях Польши, Словакии, Румынии, Швейцарии, Франции, Черногории, Канады, США, Германии и других странах.\n\n В экспозиции музея Игорь Бадяк представлять полотна, объединенные общим названием 'Вне цвета'. Это около тридцати работ, выполненных в технике беспредметного, абстрактного искусства: 'Город спит', 'Черное море', 'Золотая середина', 'Ветер. Север.' и тому подобное.\n\n Ежегодно летом художник посещает пленеры, набирается впечатлений, эмоций, опыта, а впоследствии зимними вечерами в своей мастерской на бумаге воспроизводит увиденное, ища новый, нетрадиционныю изобразительный язык. С помощью геометрических фигур, линий, пространственных тел, пятен художник демонстрирует многогранность своего таланта и неординарность мышления. Работы Игоря Бадяка побуждают к интеллектуальным размышлениям и творчеству. В то же время автор демонстрирует постоянные поиски новых выразительных форм и видения мира",
      "distance":"1934",
      "startTime":"2017-12-25T12:00:00+0200",
      "endTime":"2017-12-31T00:00:00+0200",
      "timeFromNow":82212,
      "isCancelled":false,
      "isDraft":false,
      "category":"exhibition",
      "place":{"id":"165164907333772",
        "name":"Львовский музей истории религии",
        "location":{
          "city":"Lviv",
          "country":"Ukraine",
          "latitude":49.82239443,
          "longitude":24.03263881,
          "street":"Museyna str. 1",
          "zip":"UA-79011"
          }
      },
      "stats":{
        "attending":1000,
        "declined":0,
        "maybe":102,
        "noreply":170
      },
      "venue":{
        "id":"165164907333772",
        "name":"Львовский музей истории религии",
        "about":null,
        "emails":["museum@gmail.com","museum@gmail.com"],
  "coverPicture":"https://i2.wp.com/photo-lviv.in.ua/wp-content/uploads/2017/11/Zolota-seredina.jpg?resize=696%2C680",
  "profilePicture":"https://i0.wp.com/photo-lviv.in.ua/wp-content/uploads/2017/11/Misto-spit.jpg?resize=696%2C481",
  "category":"Nonprofit Organization",
  "categoryList":["Nonprofit Organization"],
  "location":{
    "city":"Lviv",
    "country":"Ukraine",
    "latitude":49.82239443,
    "longitude":24.03263881,
    "street":"Museyna str. 1",
    "zip":"UA-79011"
    }
    }
    },
    {"id":"5",
      "name":"Новогодний праздничный Гала-Концерт",
      "type":"public",
      "coverPicture":"http://www.dolcetto.ca/site/wp-content/uploads/2015/12/nyedinner.jpg",
      "profilePicture":"http://www.dolcetto.ca/site/wp-content/uploads/2015/12/nyedinner.jpg",
      "description":"Львовская областная филармония представляет!\n\n Произведения Вольфганга Амадея Моцарта, Джузеппе Верди, Жоржа Бизе, Франца Легара, Иоганна Штрауса.\n\n Академический симфонический оркестр Львовской филармонии, Тарас Крыса - дирижер.",
      "distance":"1934",
      "startTime":"2017-12-27T19:00:00+0200",
      "endTime":"2017-12-27T22:00:00+0200",
      "timeFromNow":82212,
      "isCancelled":false,
      "isDraft":false,
      "category":"other",
      "place":{"id":"165164907333772",
        "name":"Львовская областная филармония",
        "location":{
          "city":"Lviv",
          "country":"Ukraine",
          "latitude":49.82239443,
          "longitude":24.03263881,
          "street":"Chaykovskogo str. 7",
          "zip":"UA-79011"
          }
      },
      "stats":{
        "attending":1000,
        "declined":0,
        "maybe":102,
        "noreply":170
      },
      "venue":{
        "id":"165164907333772",
        "name":"Львовская областная филармония",
        "about":null,
        "emails":["music@gmail.com","music@gmail.com"],
  "coverPicture":"https://media.timeout.com/images/12320/image.jpg",
  "profilePicture":"https://www.s.032.ua/section/afisha_event/upload/pers/40/img/afisha/000/000/027/27-12-20175a17573eb9f30.jpg",
  "category":"Philharmonic ",
  "categoryList":["Profit Organization"],
  "location":{
    "city":"Lviv",
    "country":"Ukraine",
    "latitude":49.82239443,
    "longitude":24.03263881,
    "street":"Chaykovskogo str. 7",
    "zip":"UA-79011"
    }
    }
  },
  {"id":"6",
    "name":"Ночь перед Рождеством",
    "type":"public",
    "coverPicture":"https://teatrarium.com/wp-content/uploads/2016/11/%D0%BD%D1%96%D1%87-%D0%BF%D0%B5%D1%80%D0%B5%D0%B4-%D1%80%D1%96%D0%B7%D0%B4%D0%B2%D0%BE%D0%BC-%D0%BA%D0%BE%D0%BB%D1%8F%D0%B4%D0%BD%D0%B8%D0%BA%D0%B8.jpg",
    "profilePicture":"https://teatrarium.com/wp-content/uploads/2016/11/%D0%BD%D1%96%D1%87-%D0%BF%D0%B5%D1%80%D0%B5%D0%B4-%D1%80%D1%96%D0%B7%D0%B4%D0%B2%D0%BE%D0%BC-%D0%BE%D0%B1%D0%BA%D0%BB%D0%B0%D0%B4%D0%B8%D0%BD%D0%BA%D0%B0.jpg",
    "description":"Музыкальная комедия «Ночь перед Рождеством» создана по мотивам одноименной повести классика украинской литературы Николая Гоголя режиссером-постановщиком, заслуженным артистом Украины Андреем Бакировым.\n\n К каким только изыскам не прибегают исполнители, чтобы создать на сцене волшебную, сказочную атмосферу праздничной Рождественской ночи. Здесь причудливо переплелись древние легенды и картины жизни тогдашнего украинского села, реальное и воображаемое, фантастическое и комическое. Захватывающие ритмы хореографических композиций, впечатляющая энергетика юношеского задора, колоритные сценические образы, созданные ярким актерским ансамблем, несомненно, произведут глубокое впечатление на каждого, кто познакомится с новационной работой исполнителей.",
    "distance":"1934",
    "startTime":"2018-01-03T19:00:00+0200",
    "endTime":"2018-01-03T22:00:00+0200",
    "timeFromNow":82212,
    "isCancelled":false,
    "isDraft":false,
    "category":"other",
    "place":{"id":"165164907333772",
      "name":"Львовский театр оперы и балета",
      "location":{
        "city":"Lviv",
        "country":"Ukraine",
        "latitude":49.82239443,
        "longitude":24.03263881,
        "street":"Svobody avenue 28",
        "zip":"UA-79011"
        }
    },
    "stats":{
      "attending":1000,
      "declined":0,
      "maybe":102,
      "noreply":170
    },
    "venue":{
      "id":"165164907333772",
      "name":"Львовский театр оперы и балета",
      "about":null,
      "emails":["theater@gmail.com","theater@gmail.com"],
  "coverPicture":"https://teatrarium.com/wp-content/uploads/2016/11/%D0%BD%D1%96%D1%87-%D0%BF%D0%B5%D1%80%D0%B5%D0%B4-%D1%80%D1%96%D0%B7%D0%B4%D0%B2%D0%BE%D0%BC-%D0%BA%D0%BE%D0%BB%D1%8F%D0%B4%D0%BD%D0%B8%D0%BA%D0%B8.jpg",
  "profilePicture":"https://teatrarium.com/wp-content/uploads/2016/11/%D0%BD%D1%96%D1%87-%D0%BF%D0%B5%D1%80%D0%B5%D0%B4-%D1%80%D1%96%D0%B7%D0%B4%D0%B2%D0%BE%D0%BC-%D0%BE%D0%B1%D0%BA%D0%BB%D0%B0%D0%B4%D0%B8%D0%BD%D0%BA%D0%B0.jpg",
  "category":"Theather",
  "categoryList":["Profit Organization"],
  "location":{
  "city":"Lviv",
  "country":"Ukraine",
  "latitude":49.82239443,
  "longitude":24.03263881,
  "street":"Svobody avenue 28",
  "zip":"UA-79011"
  }
  }
},
{"id":"7",
  "name":"Инфанта Маргарита",
  "type":"public",
  "coverPicture":"https://www.s.032.ua/section/afisha_event/upload/pers/40/img/afisha/000/000/027/Margarita5a201e09d5bfa.jpg",
  "profilePicture":"http://www.matrony.ru/wp-content/uploads/2014/06/7.Diego-Velaskes.-Infanta-Margarita-v-rozovom.-1660.-e1403092217628.jpg",
  "description":"Портрет инфанты Маргариты имеет большую музейную и историческую ценность и дает представление о высоком художественном уровне 'золотого века' испанской живописи, который приписывается Диего Веласкесу.\n\n Портрет Инфанты Маргариты (Маргариты Терезы) происходит из коллекции основателей музея Богдана и Варвары Ханенко. Картина была приобретена 1912 в Берлине на аукционной распродаже собрания гамбургского коллекционера Вебера. На торги произведение попало после долгого странствования частными коллекциями. Первые документальные свидетельства о картине достигают 1827, когда она еще принадлежала испанскому художнику Викену Лопесу-И-Портанья и вскоре попала в собственность инфанта Испании и Португалии Себастьяна Габриэля де Бурбон и де Браганса. В наследников инфанта, которые в то время жили во Франции, в городке По , произведение в 1891 приобрел лондонский антикварный дом Колнеги. Однако уже в следующем году портрет был перепродан немецком консулу Эдуарду Веберу.\n\n Все это время картина считалась портретом другой принцессы - инфанты Марианны Весы (1638-1683), старшей дочери Филиппа IV е первого брака. В дальнейшем она стала королевой Франции, женой Людовика ХIV. Только в предвоенные годы было выяснено, что портретируемого девочка - младшая дочь короля, ребенок его второй жены Марианны Австрийской.",
  "distance":"1934",
  "startTime":"2017-12-27T12:00:00+0200",
  "endTime":"2017-12-27T23:00:00+0200",
  "timeFromNow":82212,
  "isCancelled":false,
  "isDraft":false,
  "category":"exhibition",
  "place":{"id":"165164907333772",
    "name":"Дворец Потоцких",
    "location":{
      "city":"Lviv",
      "country":"Ukraine",
      "latitude":49.82239443,
      "longitude":24.03263881,
      "street":"Kopernika str. 15",
      "zip":"UA-79011"
      }
  },
  "stats":{
    "attending":1000,
    "declined":0,
    "maybe":102,
    "noreply":170
  },
  "venue":{
    "id":"165164907333772",
    "name":"Дворец Потоцких",
    "about":null,
    "emails":["palace@gmail.com","palace@gmail.com"],
"coverPicture":"https://www.s.032.ua/section/afisha_event/upload/pers/40/img/afisha/000/000/027/Margarita5a201e09d5bfa.jpg",
"profilePicture":"http://www.matrony.ru/wp-content/uploads/2014/06/7.Diego-Velaskes.-Infanta-Margarita-v-rozovom.-1660.-e1403092217628.jpg",
"category":"Nonprofit Organization",
"categoryList":["Nonprofit Organization"],
"location":{
"city":"Lviv",
"country":"Ukraine",
"latitude":49.82239443,
"longitude":24.03263881,
"street":"Kopernika str. 15",
"zip":"UA-79011"
}
}
},
{"id":"8",
  "name":"Рождественская история",
  "type":"public",
  "coverPicture":"https://c.tadst.com/gfx/750w/christmas.jpg?1",
  "profilePicture":"https://afisha.lviv.ua/sites/image.life/styles/vertical_middle/public/company255/events-1218-450600-5277-kb.jpg?itok=o-gxNE6B",
  "description":"Лилия Викарук - автор проекта, мама.\n\n Трио бандуристок 'Львовянки' - Ангелы.\n\n Станислав Гоян – Ослик.\n\n Оксана Ковальова – Овечка.\n\n Михаил Грыньо – Верблюд.\n\n Ансамбль 'Небесные крылья' - малые колядники.\n\n Остап Грудовый – Миша.\n\n Соломия Яковенко – Соломия.\n\n Любовь Фитьо - режиссер-постановщик.\n\n",
  "distance":"1934",
  "startTime":"2017-12-26T19:00:00+0200",
  "endTime":"2017-12-26T22:00:00+0200",
  "timeFromNow":82212,
  "isCancelled":false,
  "isDraft":false,
  "category":"other",
  "place":{"id":"165164907333772",
    "name":"Львовская областная филармония",
    "location":{
      "city":"Lviv",
      "country":"Ukraine",
      "latitude":49.82239443,
      "longitude":24.03263881,
      "street":"Chaykovskogo str. 7",
      "zip":"UA-79011"
      }
  },
  "stats":{
    "attending":1000,
    "declined":0,
    "maybe":102,
    "noreply":170
  },
  "venue":{
    "id":"165164907333772",
    "name":"Львовская областная филармония",
    "about":null,
    "emails":["music@gmail.com","music@gmail.com"],
"coverPicture":"https://media.timeout.com/images/12320/image.jpg",
"profilePicture":"https://www.s.032.ua/section/afisha_event/upload/pers/40/img/afisha/000/000/027/27-12-20175a17573eb9f30.jpg",
"category":"Philharmonic ",
"categoryList":["Profit Organization"],
"location":{
"city":"Lviv",
"country":"Ukraine",
"latitude":49.82239443,
"longitude":24.03263881,
"street":"Chaykovskogo str. 7",
"zip":"UA-79011"
}
}
},
{"id":"9",
  "name":"Выставка 'Портрет города'",
  "type":"public",
  "coverPicture":"https://afisha.lviv.ua/sites/image.life/company137/events-3776-24774825101563044664305793423552269183520962n-10269-kb.jpg",
  "profilePicture":"https://afisha.lviv.ua/sites/image.life/company137/events-3776-24774825101563044664305793423552269183520962n-10269-kb.jpg",
  "description":"Выставка призвана представить образ Львова в один из важнейших отрезков его истории - период после первого раздела Речи Посполитой (1772), когда Галичина переходит в состав Австрийской империи. Город становится столицей Королевства Галиции и Владимирии, образованного на территории бывшего Галицкого княжества. Административная, образовательная, религиозная и крестьянская реформы, которые проводят в Галиции австрийские правители Мария Терезия (1717 - 1780) и Иосиф II (1741 - 1790), меняют лицо Львова и его жизненный уклад.\n\n Представленные на выставке произведения (виды Львова и портреты львовян), относящихся к концу XVIII - первой половины XIX в. и принадлежат тогдашним художникам, которые работали во Львове и стали очевидцами событий, являются лучшими аутентичными документами своей эпохи. \n\n На выставке будут представлены произведения Йозефа Пичмана, Кароля Швейкарта, Алойзи Рехана, Яна Машковского, Мартина Яблонского, Юлиуша Коссака, Карла Ауэра, Карла Аренда и многих других. Ретроспективный характер ее экспозиции позволит вернуть зрителя в прошлое, окунуть в атмосферу тогдашнего Львова, почувствовать его дух, настроение, узнать о жизни его жителей и их обычаи, культуру, искусство, образование, политику. В экспозицию выставки войдут произведения, принадлежащие Национальному музею во Львове имени Андрея Шептицкого, Львовской национальной галереи искусств им. Б.Возницкого, Львовской национальной научной библиотеке Украины им. В. Стефаника, Львовскому историческому музею, Музея этнографии и художественного промысла Института народоведения НАН Украины и частным коллекционерам.",
  "distance":"1934",
  "startTime":"2017-12-26T12:00:00+0200",
  "endTime":"2018-02-06T22:00:00+0200",
  "timeFromNow":82212,
  "isCancelled":false,
  "isDraft":false,
  "category":"exhibition",
  "place":{"id":"165164907333772",
    "name":"Национальный музей имени Андрея Шептицкого",
    "location":{
      "city":"Lviv",
      "country":"Ukraine",
      "latitude":49.82239443,
      "longitude":24.03263881,
      "street":"Svobody avenue 20",
      "zip":"UA-79011"
      }
  },
  "stats":{
    "attending":1000,
    "declined":0,
    "maybe":102,
    "noreply":170
  },
  "venue":{
    "id":"165164907333772",
    "name":"Национальный музей имени Андрея Шептицкого",
    "about":null,
    "emails":["museum@gmail.com","museum@gmail.com"],
"coverPicture":"https://afisha.lviv.ua/sites/image.life/company137/events-3776-24774825101563044664305793423552269183520962n-10269-kb.jpg",
"profilePicture":"https://afisha.lviv.ua/sites/image.life/company137/events-3776-24774825101563044664305793423552269183520962n-10269-kb.jpg",
"category":"Museum",
"categoryList":["Profit Organization"],
"location":{
"city":"Lviv",
"country":"Ukraine",
"latitude":49.82239443,
"longitude":24.03263881,
"street":"Svobody avenue 20",
"zip":"UA-79011"
}
}
},
{"id":"10",
  "name":"Тропинка Святого Николая",
  "type":"public",
  "coverPicture":"https://ukr.media/static/ba/aimg/2/8/2/282442_1.jpg",
  "profilePicture":"https://ukr.media/static/ba/aimg/2/8/2/282442_1.jpg",
  "description":"Режиссер-постановщик Мысак Ю. А.\n\n Художник-постановщик Завьялова Д. А.\n\n Композитор з.д.м. Саенко Ю. Р.\n\n Балетмейстер Шит Т.\n\n Ассистент режиссера Гулюк И. И.\n\n С началом зимы все ждут святого Николая, который приходит с ангелочками к нам каждый год, принося радость и подарки - кто что заслужил. Однако не все знают, что для того, чтобы Николай спустился с небес, звезды указывают ему путь на землю. Или же сможет добраться до нас Николай, если хитрый Черт, сговорившись с Волком, скроет звезды? Конечно, сможет, потому что в такую волшебную ночь даже Зайцы могут стать храбрыми (если сумеют быть дружественными), а свет искренних сердец способно светить сильнее, чем звезды.",
  "distance":"1934",
  "startTime":"2017-12-27T12:00:00+0200",
  "endTime":"2018-12-27T22:00:00+0200",
  "timeFromNow":82212,
  "isCancelled":false,
  "isDraft":false,
  "category":"other",
  "place":{"id":"165164907333772",
    "name":"Первый театр",
    "location":{
      "city":"Lviv",
      "country":"Ukraine",
      "latitude":49.82239443,
      "longitude":24.03263881,
      "street":"Gnatyuka str. 11",
      "zip":"UA-79011"
      }
  },
  "stats":{
    "attending":1000,
    "declined":0,
    "maybe":102,
    "noreply":170
  },
  "venue":{
    "id":"165164907333772",
    "name":"Первый театр",
    "about":null,
    "emails":["theatre@gmail.com","theatre@gmail.com"],
"coverPicture":"https://afisha.lviv.ua/sites/image.life/styles/vertical_middle/public/company131/events-763-tyug-12469-kb.png?itok=mPsTzZhV",
"profilePicture":"https://afisha.lviv.ua/sites/image.life/users/virtual.ua.jpg",
"category":"Theatre",
"categoryList":["Profit Organization"],
"location":{
"city":"Lviv",
"country":"Ukraine",
"latitude":49.82239443,
"longitude":24.03263881,
"street":"Gnatyuka str. 11",
"zip":"UA-79011"
}
}
},
{"id":"11",
  "name":"Грандиозное шоу для всей семьи 'Холодное сердце'",
  "type":"public",
  "coverPicture":"http://www.susieseiter.com/wp-content/uploads/2017/05/Frozen-Live.jpeg",
  "profilePicture":"https://tms.net.ua/files/2017/12/07/poster_C_UH-_G.jpg",
  "description":"'Холодное сердце' - масштабная постановка от одесского продюсерского центра 'Made in odessa' - невероятная представление, созданная по мотивам любимого мультфильма детей всего мира, и самого кассового в истории компании 'Walt Disney'. История удивит новыми фактами: появлением героев, с которыми зритель не был знаком ранее и неожиданными поворотами сюжета, объединенными в оригинальный, наполненный волшебными событиями сценарий.\n\n 'Холодное сердце' - это яркое, захватывающее, в своем роде уникальное шоу для всей семьи! Масштабность постановки, невероятные приключения, более 40 персонажей, грандиозные декорации, яркие костюмы, великолепная музыка, захватывающее огненное шоу, головокружительные акробатические трюки, современная хореография - дарят зрителям ощущение праздника! Чудеса в виде спецэффектов и интерактивные моменты, во время которых гости принимают непосредственное участие в ряде фантастических событий, приводят в восторг детей и поражают взрослых!",
  "distance":"1934",
  "startTime":"2017-01-09T18:00:00+0200",
  "endTime":"2017-01-09T21:00:00+0200",
  "timeFromNow":82212,
  "isCancelled":false,
  "isDraft":false,
  "category":"family",
  "place":{"id":"165164907333772",
    "name":"Львовская областная филармония",
    "location":{
      "city":"Lviv",
      "country":"Ukraine",
      "latitude":49.82239443,
      "longitude":24.03263881,
      "street":"Chaykovskogo str. 7",
      "zip":"UA-79011"
      }
  },
  "stats":{
    "attending":1000,
    "declined":0,
    "maybe":102,
    "noreply":170
  },
  "venue":{
    "id":"165164907333772",
    "name":"Львовская областная филармония",
    "about":null,
    "emails":["music@gmail.com","music@gmail.com"],
"coverPicture":"http://www.susieseiter.com/wp-content/uploads/2017/05/Frozen-Live.jpeg",
"profilePicture":"https://tms.net.ua/files/2017/12/07/poster_C_UH-_G.jpg",
"category":"Philharmonic ",
"categoryList":["Profit Organization"],
"location":{
"city":"Lviv",
"country":"Ukraine",
"latitude":49.82239443,
"longitude":24.03263881,
"street":"Chaykovskogo str. 7",
"zip":"UA-79011"
}
}
},
{"id":"12",
  "name":"Crazy Town | Tour Poster (Eastern Europe)",
  "type":"public",
  "coverPicture":"https://tms.net.ua/files/2017/12/05/poster_Nl329SU.jpg",
  "profilePicture":"https://tms.net.ua/files/2017/12/05/poster_Nl329SU.jpg",
  "description":"Впервые во Львове американская рэпкор группа Crazytown известна благодаря хиту 'Butterfly'\n\n CRAZY TOWN (USA)\n\n FOR THE WIN (USA)\n\n CONFESSIONS OF A TRAITOR (UK)",
  "distance":"1934",
  "startTime":"2018-01-24T20:00:00+0200",
  "endTime":"2018-01-25T02:00:00+0200",
  "timeFromNow":82212,
  "isCancelled":false,
  "isDraft":false,
  "category":"night life",
  "place":{"id":"165164907333772",
    "name":"!FEST REPUBLIC",
    "location":{
      "city":"Lviv",
      "country":"Ukraine",
      "latitude":49.82239443,
      "longitude":24.03263881,
      "street":"Staroznesenska str. 24-26",
      "zip":"UA-79011"
      }
  },
  "stats":{
    "attending":1000,
    "declined":0,
    "maybe":102,
    "noreply":170
  },
  "venue":{
    "id":"165164907333772",
    "name":"!FEST REPUBLIC",
    "about":null,
    "emails":["club@gmail.com","club@gmail.com"],
"coverPicture":"https://encrypted-tbn0.gstatic.com/images?q=tbn:ANd9GcTaoJ3GEY37cPktMd5fhcrqJRptY2Sc2ielNCGqhD0fYZqNFzg3kQ",
"profilePicture":"https://encrypted-tbn0.gstatic.com/images?q=tbn:ANd9GcTaoJ3GEY37cPktMd5fhcrqJRptY2Sc2ielNCGqhD0fYZqNFzg3kQ",
"category":"Night club",
"categoryList":["Profit Organization"],
"location":{
"city":"Lviv",
"country":"Ukraine",
"latitude":49.82239443,
"longitude":24.03263881,
"street":"Staroznesenska str. 24-26",
"zip":"UA-79011"
}
}
}
  ]
  }
}
